fes_calculator/__init__.py
fes_calculator/fes_calculator.py
fes_calculator-0.1.0.dist-info/METADATA
fes_calculator-0.1.0.dist-info/WHEEL
fes_calculator-0.1.0.dist-info/entry_points.txt
fes_calculator-0.1.0.dist-info/top_level.txt
fes_calculator-0.1.0.dist-info/RECORD
