Metadata-Version: 2.4
Name: fes_calculator
Version: 0.1.0
Summary: A tool for calculating Free Energy Surfaces with MPI support.
Author-email: Your Name <your.email@example.com>
License: MIT License
Classifier: Programming Language :: Python :: 3
Classifier: License :: OSI Approved :: MIT License
Classifier: Operating System :: OS Independent
Classifier: Topic :: Scientific/Engineering :: Chemistry
Classifier: Topic :: Scientific/Engineering :: Physics
Requires-Python: >=3.7
Requires-Dist: numpy
Requires-Dist: tqdm
Requires-Dist: matplotlib
Requires-Dist: scipy
Provides-Extra: mpi
Requires-Dist: mpi4py; extra == "mpi"
